{"assets":{"FF3CC4C1690EBFC336B569AD818503F8":{"type":"texture","index":415,"assetRequest":{"type":"slide","state":"text","slide":"AFF8EF4C-6FC6-40B6-97B4-DD60A7BBCC3A"},"url":"assets/FF3CC4C1690EBFC336B569AD818503F8.svg","width":135,"height":49},"29860A4B0A24BD2A15089EA811089764":{"type":"texture","index":417,"assetRequest":{"type":"slide","state":"text","slide":"AFF8EF4C-6FC6-40B6-97B4-DD60A7BBCC3A"},"url":"assets/29860A4B0A24BD2A15089EA811089764.svg","width":349,"height":59},"ABFB53E36D1904BADCB2552C2F842730":{"type":"texture","index":421,"assetRequest":{"type":"slide","state":"object","slide":"AFF8EF4C-6FC6-40B6-97B4-DD60A7BBCC3A"},"url":"assets/ABFB53E36D1904BADCB2552C2F842730.svg","width":944,"height":943},"2669DFB488A018FBD24B4099CC30365F":{"type":"texture","index":416,"assetRequest":{"type":"slide","state":"text","slide":"AFF8EF4C-6FC6-40B6-97B4-DD60A7BBCC3A"},"url":"assets/2669DFB488A018FBD24B4099CC30365F.svg","width":329,"height":56},"03A700F694C19CBF914C99E266C25F0D":{"type":"texture","index":423,"assetRequest":{"type":"slide","state":"text","slide":"AFF8EF4C-6FC6-40B6-97B4-DD60A7BBCC3A"},"url":"assets/03A700F694C19CBF914C99E266C25F0D.svg","width":572,"height":113},"0BB9A8DC3940BD163F1907342A5D26F8":{"type":"texture","index":419,"assetRequest":{"type":"slide","state":"text","slide":"AFF8EF4C-6FC6-40B6-97B4-DD60A7BBCC3A"},"url":"assets/0BB9A8DC3940BD163F1907342A5D26F8.svg","width":362,"height":49},"0AC018AA8FBCE68F03BCD66829515547":{"type":"texture","index":418,"assetRequest":{"type":"slide","state":"text","slide":"AFF8EF4C-6FC6-40B6-97B4-DD60A7BBCC3A"},"url":"assets/0AC018AA8FBCE68F03BCD66829515547.svg","width":362,"height":49},"5561CD8E7383DBF5567B967881EA5AE7":{"type":"texture","index":420,"assetRequest":{"type":"slide","state":"text","slide":"AFF8EF4C-6FC6-40B6-97B4-DD60A7BBCC3A"},"url":"assets/5561CD8E7383DBF5567B967881EA5AE7.svg","width":712,"height":59},"B6B6695CE5F36342F41B6C89CDAD41EF":{"type":"texture","index":414,"assetRequest":{"type":"slide","state":"object","slide":"AFF8EF4C-6FC6-40B6-97B4-DD60A7BBCC3A"},"url":"assets/B6B6695CE5F36342F41B6C89CDAD41EF.svg","width":1920,"height":1082},"16C25E2DB6A5BE53985A40D561AB279C":{"type":"texture","index":413,"assetRequest":{"type":"slide","state":"object","slide":"AFF8EF4C-6FC6-40B6-97B4-DD60A7BBCC3A"},"url":"assets/16C25E2DB6A5BE53985A40D561AB279C.svg","width":1930,"height":1082},"6B9D1A58EFD59BF98F533428FC1923C5":{"type":"texture","index":412,"assetRequest":{"type":"slide","state":"object","slide":"AFF8EF4C-6FC6-40B6-97B4-DD60A7BBCC3A"},"url":"assets/6B9D1A58EFD59BF98F533428FC1923C5.svg","width":1923,"height":1082},"5BA6DF7ACEF516F7DAB78587CF30CE20":{"type":"texture","index":411,"assetRequest":{"type":"slide","state":"background","slide":"AFF8EF4C-6FC6-40B6-97B4-DD60A7BBCC3A"},"url":"assets/5BA6DF7ACEF516F7DAB78587CF30CE20.svg","width":1920,"height":1080},"A5BBE620C3D5C2D755DCB8E756B0AAED":{"type":"texture","index":422,"assetRequest":{"type":"slide","state":"text","slide":"AFF8EF4C-6FC6-40B6-97B4-DD60A7BBCC3A"},"url":"assets/A5BBE620C3D5C2D755DCB8E756B0AAED.svg","width":628,"height":89}},"events":[{"effects":[{"beginTime":0,"baseLayer":{"animations":[],"initialState":{"affineTransform":[1,0,0,1,0,0],"masksToBounds":true,"rotation":0,"scale":1,"position":{"pointX":960,"pointY":540},"width":1920,"sublayerTransform":[1,0,0,0,0,1,0,0,0,0,1,0,0,0,0,1],"contentsRect":{"y":0,"x":0,"width":1,"height":1},"opacity":1,"edgeAntialiasingMask":0,"height":1080,"hidden":false,"anchorPoint":{"pointX":0.5,"pointY":0.5}},"objectID":"0","layers":[{"animations":[],"initialState":{"affineTransform":[1,0,0,1,0,0],"masksToBounds":false,"rotation":0,"scale":1,"position":{"pointX":960,"pointY":540},"width":1920,"sublayerTransform":[1,0,0,0,0,1,0,0,0,0,1,-0.0003500791246677598,0,0,0,1],"contentsRect":{"y":0,"x":0,"width":1,"height":1},"opacity":1,"edgeAntialiasingMask":15,"height":1080,"hidden":false,"anchorPoint":{"pointX":0.5,"pointY":0.5}},"layers":[{"animations":[{"repeatCount":0,"animations":[{"from":{"scalar":0},"beginTime":0,"repeatCount":0,"fillMode":"both","property":"zPosition","duration":1,"timingFunction":"easeInEaseOut","to":{"scalar":0}}],"beginTime":0,"fillMode":"both","duration":1}],"initialState":{"affineTransform":[1,0,0,1,0,0],"masksToBounds":false,"rotation":0,"scale":1,"position":{"pointX":960,"pointY":540},"width":1920,"sublayerTransform":[1,0,0,0,0,1,0,0,0,0,1,0,0,0,0,1],"contentsRect":{"y":0,"x":0,"width":1,"height":1},"opacity":1,"edgeAntialiasingMask":15,"height":1080,"hidden":false,"anchorPoint":{"pointX":0.5,"pointY":0.5}},"layers":[{"animations":[{"repeatCount":0,"animations":[{"from":{"texture":"5BA6DF7ACEF516F7DAB78587CF30CE20"},"beginTime":0,"repeatCount":0,"fillMode":"both","property":"contents","duration":1,"timingFunction":"easeInEaseOut","to":{"texture":"5BA6DF7ACEF516F7DAB78587CF30CE20"}}],"beginTime":0,"fillMode":"both","duration":1}],"layers":[],"initialState":{"affineTransform":[1,0,0,1,0,0],"masksToBounds":false,"rotation":0,"scale":1,"position":{"pointX":960,"pointY":540},"width":1920,"sublayerTransform":[1,0,0,0,0,1,0,0,0,0,1,0,0,0,0,1],"contentsRect":{"y":0,"x":0,"width":1,"height":1},"opacity":1,"edgeAntialiasingMask":0,"height":1080,"hidden":false,"anchorPoint":{"pointX":0.5,"pointY":0.5}},"texture":"5BA6DF7ACEF516F7DAB78587CF30CE20"}]}]},{"animations":[{"repeatCount":0,"animations":[{"from":{"scalar":0.001},"beginTime":0,"repeatCount":0,"fillMode":"both","property":"zPosition","duration":1,"timingFunction":"easeInEaseOut","to":{"scalar":0.001}}],"beginTime":0,"fillMode":"both","duration":1}],"initialState":{"affineTransform":[1,0,0,1,0,0],"masksToBounds":false,"rotation":0,"scale":1,"position":{"pointX":960.5387573242188,"pointY":540},"width":1919.348999023438,"sublayerTransform":[1,0,0,0,0,1,0,0,0,0,1,0,0,0,0,1],"contentsRect":{"y":0,"x":0,"width":1,"height":1},"opacity":1,"edgeAntialiasingMask":15,"height":1079.6337890625,"hidden":false,"anchorPoint":{"pointX":0.5,"pointY":0.5}},"layers":[{"animations":[{"repeatCount":0,"animations":[{"from":{"texture":"6B9D1A58EFD59BF98F533428FC1923C5"},"beginTime":0,"repeatCount":0,"fillMode":"both","property":"contents","duration":1,"timingFunction":"easeInEaseOut","to":{"texture":"6B9D1A58EFD59BF98F533428FC1923C5"}}],"beginTime":0,"fillMode":"both","duration":1}],"layers":[],"initialState":{"affineTransform":[1,0,0,1,0,0],"masksToBounds":false,"rotation":0,"scale":1,"position":{"pointX":959.6744995117188,"pointY":539.81689453125},"width":1923,"sublayerTransform":[1,0,0,0,0,1,0,0,0,0,1,0,0,0,0,1],"contentsRect":{"y":0,"x":0,"width":1,"height":1},"opacity":1,"edgeAntialiasingMask":0,"height":1082,"hidden":false,"anchorPoint":{"pointX":0.5000201546147783,"pointY":0.5}},"texture":"6B9D1A58EFD59BF98F533428FC1923C5"}]},{"animations":[{"repeatCount":0,"animations":[{"from":{"scalar":0.002},"beginTime":0,"repeatCount":0,"fillMode":"both","property":"zPosition","duration":1,"timingFunction":"easeInEaseOut","to":{"scalar":0.002}}],"beginTime":0,"fillMode":"both","duration":1}],"initialState":{"affineTransform":[1,0,0,1,0,0],"masksToBounds":false,"rotation":0,"scale":1,"position":{"pointX":960.5451202392578,"pointY":540.0014553070068},"width":1927.03125,"sublayerTransform":[1,0,0,0,0,1,0,0,0,0,1,0,0,0,0,1],"contentsRect":{"y":0,"x":0,"width":1,"height":1},"opacity":1,"edgeAntialiasingMask":15,"height":1078.28125,"hidden":false,"anchorPoint":{"pointX":0.5,"pointY":0.5}},"layers":[{"animations":[{"repeatCount":0,"animations":[{"from":{"texture":"16C25E2DB6A5BE53985A40D561AB279C"},"beginTime":0,"repeatCount":0,"fillMode":"both","property":"contents","duration":1,"timingFunction":"easeInEaseOut","to":{"texture":"16C25E2DB6A5BE53985A40D561AB279C"}}],"beginTime":0,"fillMode":"both","duration":1}],"layers":[],"initialState":{"affineTransform":[1,0,0,1,0,0],"masksToBounds":false,"rotation":0,"scale":1,"position":{"pointX":963.5092735290527,"pointY":539.1391754150391},"width":1930,"sublayerTransform":[1,0,0,0,0,1,0,0,0,0,1,0,0,0,0,1],"contentsRect":{"y":0,"x":0,"width":1,"height":1},"opacity":1,"edgeAntialiasingMask":0,"height":1082,"hidden":false,"anchorPoint":{"pointX":0.4997610200872075,"pointY":0.5000000052883973}},"texture":"16C25E2DB6A5BE53985A40D561AB279C"}]},{"animations":[{"repeatCount":0,"animations":[{"from":{"scalar":0.003},"beginTime":0,"repeatCount":0,"fillMode":"both","property":"zPosition","duration":1,"timingFunction":"easeInEaseOut","to":{"scalar":0.003}}],"beginTime":0,"fillMode":"both","duration":1}],"initialState":{"affineTransform":[1,0,0,1,0,0],"masksToBounds":false,"rotation":0,"scale":1,"position":{"pointX":960.5387420654297,"pointY":539.9999694824219},"width":1917.05615234375,"sublayerTransform":[1,0,0,0,0,1,0,0,0,0,1,0,0,0,0,1],"contentsRect":{"y":0,"x":0,"width":1,"height":1},"opacity":1,"edgeAntialiasingMask":15,"height":1078.910888671875,"hidden":false,"anchorPoint":{"pointX":0.5,"pointY":0.5}},"layers":[{"animations":[{"repeatCount":0,"animations":[{"from":{"texture":"B6B6695CE5F36342F41B6C89CDAD41EF"},"beginTime":0,"repeatCount":0,"fillMode":"both","property":"contents","duration":1,"timingFunction":"easeInEaseOut","to":{"texture":"B6B6695CE5F36342F41B6C89CDAD41EF"}}],"beginTime":0,"fillMode":"both","duration":1}],"layers":[],"initialState":{"affineTransform":[1,0,0,1,0,0],"masksToBounds":false,"rotation":0,"scale":1,"position":{"pointX":958.528076171875,"pointY":539.4554443359375},"width":1920,"sublayerTransform":[1,0,0,0,0,1,0,0,0,0,1,0,0,0,0,1],"contentsRect":{"y":0,"x":0,"width":1,"height":1},"opacity":1,"edgeAntialiasingMask":0,"height":1082,"hidden":false,"anchorPoint":{"pointX":0.4997597614924113,"pointY":0.4999999717952143}},"texture":"B6B6695CE5F36342F41B6C89CDAD41EF"}]},{"animations":[{"repeatCount":0,"animations":[{"from":{"scalar":0.004},"beginTime":0,"repeatCount":0,"fillMode":"both","property":"zPosition","duration":1,"timingFunction":"easeInEaseOut","to":{"scalar":0.004}}],"beginTime":0,"fillMode":"both","duration":1}],"initialState":{"affineTransform":[1,0,0,1,0,0],"masksToBounds":false,"rotation":0,"scale":1,"position":{"pointX":960.0000057220459,"pointY":540},"width":801.7939567565918,"sublayerTransform":[1,0,0,0,0,1,0,0,0,0,1,0,0,0,0,1],"contentsRect":{"y":0,"x":0,"width":1,"height":1},"opacity":1,"edgeAntialiasingMask":15,"height":467.2500133514404,"hidden":false,"anchorPoint":{"pointX":0.5,"pointY":0.5}},"layers":[{"animations":[{"repeatCount":0,"animations":[{"from":{"scalar":1},"beginTime":0,"repeatCount":0,"fillMode":"forwards","property":"opacity","duration":0.3333,"timingFunction":"easeInEaseOut","to":{"scalar":0}},{"from":{"scalar":true},"beginTime":0.3333,"repeatCount":0,"fillMode":"forwards","property":"hidden","duration":0.6667000000000001,"to":{"scalar":true}}],"beginTime":0,"fillMode":"both","duration":1}],"layers":[],"initialState":{"affineTransform":[1,0,0,1,0,0],"masksToBounds":false,"rotation":0,"scale":1,"position":{"pointX":393.39697265625,"pointY":238.6250066757202},"width":135,"sublayerTransform":[1,0,0,0,0,1,0,0,0,0,1,0,0,0,0,1],"contentsRect":{"y":0,"x":0,"width":1,"height":1},"opacity":1,"edgeAntialiasingMask":0,"height":49,"hidden":false,"anchorPoint":{"pointX":2.418518518518519,"pointY":-1.673469387755102}},"texture":"FF3CC4C1690EBFC336B569AD818503F8"}]},{"animations":[{"repeatCount":0,"animations":[{"from":{"scalar":0.005},"beginTime":0,"repeatCount":0,"fillMode":"both","property":"zPosition","duration":1,"timingFunction":"easeInEaseOut","to":{"scalar":0.005}}],"beginTime":0,"fillMode":"both","duration":1}],"initialState":{"affineTransform":[1,0,0,1,0,0],"masksToBounds":false,"rotation":0,"scale":1,"position":{"pointX":960.0000057220459,"pointY":540},"width":801.7939567565918,"sublayerTransform":[1,0,0,0,0,1,0,0,0,0,1,0,0,0,0,1],"contentsRect":{"y":0,"x":0,"width":1,"height":1},"opacity":1,"edgeAntialiasingMask":15,"height":467.2500133514404,"hidden":false,"anchorPoint":{"pointX":0.5,"pointY":0.5}},"layers":[{"animations":[{"repeatCount":0,"animations":[{"from":{"scalar":1},"beginTime":0,"repeatCount":0,"fillMode":"forwards","property":"opacity","duration":0.3333,"timingFunction":"easeInEaseOut","to":{"scalar":0}},{"from":{"scalar":true},"beginTime":0.3333,"repeatCount":0,"fillMode":"forwards","property":"hidden","duration":0.6667000000000001,"to":{"scalar":true}}],"beginTime":0,"fillMode":"both","duration":1}],"layers":[],"initialState":{"affineTransform":[1,0,0,1,0,0],"masksToBounds":false,"rotation":0,"scale":1,"position":{"pointX":393.39697265625,"pointY":238.6250066757202},"width":329,"sublayerTransform":[1,0,0,0,0,1,0,0,0,0,1,0,0,0,0,1],"contentsRect":{"y":0,"x":0,"width":1,"height":1},"opacity":1,"edgeAntialiasingMask":0,"height":56,"hidden":false,"anchorPoint":{"pointX":1.168693009118541,"pointY":3.892857142857143}},"texture":"2669DFB488A018FBD24B4099CC30365F"}]},{"animations":[{"repeatCount":0,"animations":[{"from":{"scalar":0.006},"beginTime":0,"repeatCount":0,"fillMode":"both","property":"zPosition","duration":1,"timingFunction":"easeInEaseOut","to":{"scalar":0.006}}],"beginTime":0,"fillMode":"both","duration":1}],"initialState":{"affineTransform":[1,0,0,1,0,0],"masksToBounds":false,"rotation":0,"scale":1,"position":{"pointX":960.0000057220459,"pointY":540},"width":801.7939567565918,"sublayerTransform":[1,0,0,0,0,1,0,0,0,0,1,0,0,0,0,1],"contentsRect":{"y":0,"x":0,"width":1,"height":1},"opacity":1,"edgeAntialiasingMask":15,"height":467.2500133514404,"hidden":false,"anchorPoint":{"pointX":0.5,"pointY":0.5}},"layers":[{"animations":[{"repeatCount":0,"animations":[{"from":{"scalar":1},"beginTime":0,"repeatCount":0,"fillMode":"forwards","property":"opacity","duration":0.3333,"timingFunction":"easeInEaseOut","to":{"scalar":0}},{"from":{"scalar":true},"beginTime":0.3333,"repeatCount":0,"fillMode":"forwards","property":"hidden","duration":0.6667000000000001,"to":{"scalar":true}}],"beginTime":0,"fillMode":"both","duration":1}],"layers":[],"initialState":{"affineTransform":[1,0,0,1,0,0],"masksToBounds":false,"rotation":0,"scale":1,"position":{"pointX":393.3969726562501,"pointY":238.6250066757202},"width":349,"sublayerTransform":[1,0,0,0,0,1,0,0,0,0,1,0,0,0,0,1],"contentsRect":{"y":0,"x":0,"width":1,"height":1},"opacity":1,"edgeAntialiasingMask":0,"height":59,"hidden":false,"anchorPoint":{"pointX":1.101719197707737,"pointY":-2.694915254237288}},"texture":"29860A4B0A24BD2A15089EA811089764"}]},{"animations":[{"repeatCount":0,"animations":[{"from":{"scalar":0.007},"beginTime":0,"repeatCount":0,"fillMode":"both","property":"zPosition","duration":1,"timingFunction":"easeInEaseOut","to":{"scalar":0.007}}],"beginTime":0,"fillMode":"both","duration":1}],"initialState":{"affineTransform":[1,0,0,1,0,0],"masksToBounds":false,"rotation":0,"scale":1,"position":{"pointX":960.0000057220459,"pointY":540},"width":801.7939567565918,"sublayerTransform":[1,0,0,0,0,1,0,0,0,0,1,0,0,0,0,1],"contentsRect":{"y":0,"x":0,"width":1,"height":1},"opacity":1,"edgeAntialiasingMask":15,"height":467.2500133514404,"hidden":false,"anchorPoint":{"pointX":0.5,"pointY":0.5}},"layers":[{"animations":[{"repeatCount":0,"animations":[{"from":{"scalar":1},"beginTime":0,"repeatCount":0,"fillMode":"forwards","property":"opacity","duration":0.3333,"timingFunction":"easeInEaseOut","to":{"scalar":0}},{"from":{"scalar":true},"beginTime":0.3333,"repeatCount":0,"fillMode":"forwards","property":"hidden","duration":0.6667000000000001,"to":{"scalar":true}}],"beginTime":0,"fillMode":"both","duration":1}],"layers":[],"initialState":{"affineTransform":[1,0,0,1,0,0],"masksToBounds":false,"rotation":0,"scale":1,"position":{"pointX":393.39697265625,"pointY":238.6250066757202},"width":362,"sublayerTransform":[1,0,0,0,0,1,0,0,0,0,1,0,0,0,0,1],"contentsRect":{"y":0,"x":0,"width":1,"height":1},"opacity":1,"edgeAntialiasingMask":0,"height":49,"hidden":false,"anchorPoint":{"pointX":0.7417127071823204,"pointY":-0.1224489795918368}},"texture":"0AC018AA8FBCE68F03BCD66829515547"}]},{"animations":[{"repeatCount":0,"animations":[{"from":{"scalar":0.008},"beginTime":0,"repeatCount":0,"fillMode":"both","property":"zPosition","duration":1,"timingFunction":"easeInEaseOut","to":{"scalar":0.008}}],"beginTime":0,"fillMode":"both","duration":1}],"initialState":{"affineTransform":[1,0,0,1,0,0],"masksToBounds":false,"rotation":0,"scale":1,"position":{"pointX":960.0000057220459,"pointY":540},"width":801.7939567565918,"sublayerTransform":[1,0,0,0,0,1,0,0,0,0,1,0,0,0,0,1],"contentsRect":{"y":0,"x":0,"width":1,"height":1},"opacity":1,"edgeAntialiasingMask":15,"height":467.2500133514404,"hidden":false,"anchorPoint":{"pointX":0.5,"pointY":0.5}},"layers":[{"animations":[{"repeatCount":0,"animations":[{"from":{"scalar":1},"beginTime":0,"repeatCount":0,"fillMode":"forwards","property":"opacity","duration":0.3333,"timingFunction":"easeInEaseOut","to":{"scalar":0}},{"from":{"scalar":true},"beginTime":0.3333,"repeatCount":0,"fillMode":"forwards","property":"hidden","duration":0.6667000000000001,"to":{"scalar":true}}],"beginTime":0,"fillMode":"both","duration":1}],"layers":[],"initialState":{"affineTransform":[1,0,0,1,0,0],"masksToBounds":false,"rotation":0,"scale":1,"position":{"pointX":393.39697265625,"pointY":238.6250066757202},"width":362,"sublayerTransform":[1,0,0,0,0,1,0,0,0,0,1,0,0,0,0,1],"contentsRect":{"y":0,"x":0,"width":1,"height":1},"opacity":1,"edgeAntialiasingMask":0,"height":49,"hidden":false,"anchorPoint":{"pointX":0.7417127071823204,"pointY":1.428571428571429}},"texture":"0BB9A8DC3940BD163F1907342A5D26F8"}]},{"animations":[{"repeatCount":0,"animations":[{"from":{"scalar":0.009000000000000001},"beginTime":0,"repeatCount":0,"fillMode":"both","property":"zPosition","duration":1,"timingFunction":"easeInEaseOut","to":{"scalar":0.009000000000000001}}],"beginTime":0,"fillMode":"both","duration":1}],"initialState":{"affineTransform":[1,0,0,1,0,0],"masksToBounds":false,"rotation":0,"scale":1,"position":{"pointX":960.0000057220459,"pointY":540},"width":801.7939567565918,"sublayerTransform":[1,0,0,0,0,1,0,0,0,0,1,0,0,0,0,1],"contentsRect":{"y":0,"x":0,"width":1,"height":1},"opacity":1,"edgeAntialiasingMask":15,"height":467.2500133514404,"hidden":false,"anchorPoint":{"pointX":0.5,"pointY":0.5}},"layers":[{"animations":[{"repeatCount":0,"animations":[{"from":{"scalar":1},"beginTime":0,"repeatCount":0,"fillMode":"forwards","property":"opacity","duration":0.3333,"timingFunction":"easeInEaseOut","to":{"scalar":0}},{"from":{"scalar":true},"beginTime":0.3333,"repeatCount":0,"fillMode":"forwards","property":"hidden","duration":0.6667000000000001,"to":{"scalar":true}}],"beginTime":0,"fillMode":"both","duration":1}],"layers":[],"initialState":{"affineTransform":[1,0,0,1,0,0],"masksToBounds":false,"rotation":0,"scale":1,"position":{"pointX":393.39697265625,"pointY":238.6250066757202},"width":712,"sublayerTransform":[1,0,0,0,0,1,0,0,0,0,1,0,0,0,0,1],"contentsRect":{"y":0,"x":0,"width":1,"height":1},"opacity":1,"edgeAntialiasingMask":0,"height":59,"hidden":false,"anchorPoint":{"pointX":0.4585674157303371,"pointY":2.474576271186441}},"texture":"5561CD8E7383DBF5567B967881EA5AE7"}]},{"animations":[{"repeatCount":0,"animations":[{"from":{"scalar":0.01},"beginTime":0,"repeatCount":0,"fillMode":"both","property":"zPosition","duration":1,"timingFunction":"easeInEaseOut","to":{"scalar":0.01}}],"beginTime":0,"fillMode":"both","duration":1}],"initialState":{"affineTransform":[1,0,0,1,0,0],"masksToBounds":false,"rotation":0,"scale":1,"position":{"pointX":381.643211364746,"pointY":540},"width":939.7834472656251,"sublayerTransform":[1,0,0,0,0,1,0,0,0,0,1,0,0,0,0,1],"contentsRect":{"y":0,"x":0,"width":1,"height":1},"opacity":1,"edgeAntialiasingMask":15,"height":939.7834472656251,"hidden":false,"anchorPoint":{"pointX":0.5,"pointY":0.5}},"layers":[{"animations":[{"repeatCount":0,"animations":[{"from":{"scalar":0},"beginTime":0.6667000000000001,"repeatCount":0,"fillMode":"both","property":"opacity","duration":0.3333,"timingFunction":"easeInEaseOut","to":{"scalar":1}},{"from":{"scalar":false},"beginTime":0.6667000000000001,"repeatCount":0,"fillMode":"forwards","property":"hidden","duration":0.3332999999999999,"to":{"scalar":false}}],"beginTime":0,"fillMode":"both","duration":1}],"layers":[],"initialState":{"affineTransform":[1,0,0,1,0,0],"masksToBounds":false,"rotation":0,"scale":1,"position":{"pointX":469.3918755006439,"pointY":469.3917236328127},"width":944,"sublayerTransform":[1,0,0,0,0,1,0,0,0,0,1,0,0,0,0,1],"contentsRect":{"y":0,"x":0,"width":1,"height":1},"opacity":1,"edgeAntialiasingMask":0,"height":943,"hidden":true,"anchorPoint":{"pointX":0.5001518678311201,"pointY":0.5000000000000001}},"texture":"ABFB53E36D1904BADCB2552C2F842730"}]},{"animations":[{"repeatCount":0,"animations":[{"from":{"scalar":0.011},"beginTime":0,"repeatCount":0,"fillMode":"both","property":"zPosition","duration":1,"timingFunction":"easeInEaseOut","to":{"scalar":0.011}}],"beginTime":0,"fillMode":"both","duration":1}],"initialState":{"affineTransform":[1,0,0,1,0,0],"masksToBounds":false,"rotation":0,"scale":1,"position":{"pointX":1348.625366210938,"pointY":540},"width":705.6670188903809,"sublayerTransform":[1,0,0,0,0,1,0,0,0,0,1,0,0,0,0,1],"contentsRect":{"y":0,"x":0,"width":1,"height":1},"opacity":1,"edgeAntialiasingMask":15,"height":315.2499914169312,"hidden":false,"anchorPoint":{"pointX":0.5,"pointY":0.5}},"layers":[{"animations":[{"repeatCount":0,"animations":[{"from":{"scalar":0},"beginTime":0.6667000000000001,"repeatCount":0,"fillMode":"both","property":"opacity","duration":0.3333,"timingFunction":"easeInEaseOut","to":{"scalar":1}},{"from":{"scalar":false},"beginTime":0.6667000000000001,"repeatCount":0,"fillMode":"forwards","property":"hidden","duration":0.3332999999999999,"to":{"scalar":false}}],"beginTime":0,"fillMode":"both","duration":1}],"layers":[],"initialState":{"affineTransform":[1,0,0,1,0,0],"masksToBounds":false,"rotation":0,"scale":1,"position":{"pointX":371.7081432342529,"pointY":164.1249957084656},"width":628,"sublayerTransform":[1,0,0,0,0,1,0,0,0,0,1,0,0,0,0,1],"contentsRect":{"y":0,"x":0,"width":1,"height":1},"opacity":1,"edgeAntialiasingMask":0,"height":89,"hidden":true,"anchorPoint":{"pointX":0.5246815286624203,"pointY":1.48876404494382}},"texture":"A5BBE620C3D5C2D755DCB8E756B0AAED"}]},{"animations":[{"repeatCount":0,"animations":[{"from":{"scalar":0.012},"beginTime":0,"repeatCount":0,"fillMode":"both","property":"zPosition","duration":1,"timingFunction":"easeInEaseOut","to":{"scalar":0.012}}],"beginTime":0,"fillMode":"both","duration":1}],"initialState":{"affineTransform":[1,0,0,1,0,0],"masksToBounds":false,"rotation":0,"scale":1,"position":{"pointX":1348.625366210938,"pointY":540},"width":705.6670188903809,"sublayerTransform":[1,0,0,0,0,1,0,0,0,0,1,0,0,0,0,1],"contentsRect":{"y":0,"x":0,"width":1,"height":1},"opacity":1,"edgeAntialiasingMask":15,"height":315.2499914169312,"hidden":false,"anchorPoint":{"pointX":0.5,"pointY":0.5}},"layers":[{"animations":[{"repeatCount":0,"animations":[{"from":{"scalar":0},"beginTime":0.6667000000000001,"repeatCount":0,"fillMode":"both","property":"opacity","duration":0.3333,"timingFunction":"easeInEaseOut","to":{"scalar":1}},{"from":{"scalar":false},"beginTime":0.6667000000000001,"repeatCount":0,"fillMode":"forwards","property":"hidden","duration":0.3332999999999999,"to":{"scalar":false}}],"beginTime":0,"fillMode":"both","duration":1}],"layers":[],"initialState":{"affineTransform":[1,0,0,1,0,0],"masksToBounds":false,"rotation":0,"scale":1,"position":{"pointX":371.7081432342529,"pointY":164.1249957084656},"width":572,"sublayerTransform":[1,0,0,0,0,1,0,0,0,0,1,0,0,0,0,1],"contentsRect":{"y":0,"x":0,"width":1,"height":1},"opacity":1,"edgeAntialiasingMask":0,"height":113,"hidden":true,"anchorPoint":{"pointX":0.5288461538461539,"pointY":-0.172566371681416}},"texture":"03A700F694C19CBF914C99E266C25F0D"}]}]},"effects":[],"duration":1,"type":"transition","name":"apple:magic-move-implied-motion-path","objectID":"0"}],"automaticPlay":false,"hyperlinks":[],"accessibility":[{"text":"Screen Shot 2013-11-24 at 5.06.23 PM.png","targetRectangle":{"y":0.18310546875,"x":0.8642578125,"width":1919.348999023438,"height":1079.6337890625}},{"text":"<navigation>","targetRectangle":{"y":311.9999933242798,"x":564.72802734375,"width":333.984,"height":76}},{"text":"    <ul class=“snap-container”>","targetRectangle":{"y":387.9999933242798,"x":564.72802734375,"width":774.9839999999999,"height":76}},{"text":"        <li>Link 1</li>","targetRectangle":{"y":463.9999933242798,"x":564.72802734375,"width":483.4479999999999,"height":76}},{"text":"        <li>Link 2</li>","targetRectangle":{"y":539.9999933242798,"x":564.72802734375,"width":483.4479999999999,"height":76}},{"text":"    </ul>","targetRectangle":{"y":615.9999933242798,"x":564.72802734375,"width":198.1279999999999,"height":76}},{"text":"</navigation>","targetRectangle":{"y":691.9999933242798,"x":564.72802734375,"width":354.704,"height":76}},{"text":"Screen Shot 2013-11-24 at 5.06.23 PM.png","targetRectangle":{"y":0.8608303070068359,"x":-2.970504760742188,"width":1927.03125,"height":1078.28125}}],"baseLayer":{"animations":[],"initialState":{"affineTransform":[1,0,0,1,0,0],"masksToBounds":true,"rotation":0,"scale":1,"position":{"pointX":960,"pointY":540},"width":1920,"sublayerTransform":[1,0,0,0,0,1,0,0,0,0,1,0,0,0,0,1],"contentsRect":{"y":0,"x":0,"width":1,"height":1},"opacity":1,"edgeAntialiasingMask":0,"height":1080,"hidden":false,"anchorPoint":{"pointX":0.5,"pointY":0.5}},"objectID":"0","layers":[{"animations":[],"initialState":{"affineTransform":[1,0,0,1,0,0],"masksToBounds":false,"rotation":0,"scale":1,"position":{"pointX":960,"pointY":540},"width":1920,"sublayerTransform":[1,0,0,0,0,1,0,0,0,0,1,-0.0003500791246677598,0,0,0,1],"contentsRect":{"y":0,"x":0,"width":1,"height":1},"opacity":1,"edgeAntialiasingMask":15,"height":1080,"hidden":false,"anchorPoint":{"pointX":0.5,"pointY":0.5}},"layers":[{"animations":[],"initialState":{"affineTransform":[1,0,0,1,0,0],"masksToBounds":false,"rotation":0,"scale":1,"position":{"pointX":960,"pointY":540},"width":1920,"sublayerTransform":[1,0,0,0,0,1,0,0,0,0,1,0,0,0,0,1],"contentsRect":{"y":0,"x":0,"width":1,"height":1},"opacity":1,"edgeAntialiasingMask":15,"height":1080,"hidden":false,"anchorPoint":{"pointX":0.5,"pointY":0.5}},"layers":[{"animations":[],"layers":[],"initialState":{"affineTransform":[1,0,0,1,0,0],"masksToBounds":false,"rotation":0,"scale":1,"position":{"pointX":960,"pointY":540},"width":1920,"sublayerTransform":[1,0,0,0,0,1,0,0,0,0,1,0,0,0,0,1],"contentsRect":{"y":0,"x":0,"width":1,"height":1},"opacity":1,"edgeAntialiasingMask":0,"height":1080,"hidden":false,"anchorPoint":{"pointX":0.5,"pointY":0.5}},"texture":"5BA6DF7ACEF516F7DAB78587CF30CE20"}]}]},{"animations":[],"initialState":{"affineTransform":[1,0,0,1,0,0],"masksToBounds":false,"rotation":0,"scale":1,"position":{"pointX":960.5387573242188,"pointY":540},"width":1919.348999023438,"sublayerTransform":[1,0,0,0,0,1,0,0,0,0,1,0,0,0,0,1],"contentsRect":{"y":0,"x":0,"width":1,"height":1},"opacity":1,"edgeAntialiasingMask":15,"height":1079.6337890625,"hidden":false,"anchorPoint":{"pointX":0.5,"pointY":0.5}},"layers":[{"animations":[],"layers":[],"initialState":{"affineTransform":[1,0,0,1,0,0],"masksToBounds":false,"rotation":0,"scale":1,"position":{"pointX":959.6744995117188,"pointY":539.81689453125},"width":1923,"sublayerTransform":[1,0,0,0,0,1,0,0,0,0,1,0,0,0,0,1],"contentsRect":{"y":0,"x":0,"width":1,"height":1},"opacity":1,"edgeAntialiasingMask":0,"height":1082,"hidden":false,"anchorPoint":{"pointX":0.5000201546147783,"pointY":0.5}},"texture":"6B9D1A58EFD59BF98F533428FC1923C5"}]},{"animations":[],"initialState":{"affineTransform":[1,0,0,1,0,0],"masksToBounds":false,"rotation":0,"scale":1,"position":{"pointX":960.5451202392578,"pointY":540.0014553070068},"width":1927.03125,"sublayerTransform":[1,0,0,0,0,1,0,0,0,0,1,0,0,0,0,1],"contentsRect":{"y":0,"x":0,"width":1,"height":1},"opacity":1,"edgeAntialiasingMask":15,"height":1078.28125,"hidden":false,"anchorPoint":{"pointX":0.5,"pointY":0.5}},"layers":[{"animations":[],"layers":[],"initialState":{"affineTransform":[1,0,0,1,0,0],"masksToBounds":false,"rotation":0,"scale":1,"position":{"pointX":963.5092735290527,"pointY":539.1391754150391},"width":1930,"sublayerTransform":[1,0,0,0,0,1,0,0,0,0,1,0,0,0,0,1],"contentsRect":{"y":0,"x":0,"width":1,"height":1},"opacity":1,"edgeAntialiasingMask":0,"height":1082,"hidden":false,"anchorPoint":{"pointX":0.4997610200872075,"pointY":0.5000000052883973}},"texture":"16C25E2DB6A5BE53985A40D561AB279C"}]},{"animations":[],"initialState":{"affineTransform":[1,0,0,1,0,0],"masksToBounds":false,"rotation":0,"scale":1,"position":{"pointX":960.5387420654297,"pointY":539.9999694824219},"width":1917.05615234375,"sublayerTransform":[1,0,0,0,0,1,0,0,0,0,1,0,0,0,0,1],"contentsRect":{"y":0,"x":0,"width":1,"height":1},"opacity":1,"edgeAntialiasingMask":15,"height":1078.910888671875,"hidden":false,"anchorPoint":{"pointX":0.5,"pointY":0.5}},"layers":[{"animations":[],"layers":[],"initialState":{"affineTransform":[1,0,0,1,0,0],"masksToBounds":false,"rotation":0,"scale":1,"position":{"pointX":958.528076171875,"pointY":539.4554443359375},"width":1920,"sublayerTransform":[1,0,0,0,0,1,0,0,0,0,1,0,0,0,0,1],"contentsRect":{"y":0,"x":0,"width":1,"height":1},"opacity":1,"edgeAntialiasingMask":0,"height":1082,"hidden":false,"anchorPoint":{"pointX":0.4997597614924113,"pointY":0.4999999717952143}},"texture":"B6B6695CE5F36342F41B6C89CDAD41EF"}]},{"animations":[],"initialState":{"affineTransform":[1,0,0,1,0,0],"masksToBounds":false,"rotation":0,"scale":1,"position":{"pointX":960.0000057220459,"pointY":540},"width":801.7939567565918,"sublayerTransform":[1,0,0,0,0,1,0,0,0,0,1,0,0,0,0,1],"contentsRect":{"y":0,"x":0,"width":1,"height":1},"opacity":1,"edgeAntialiasingMask":15,"height":467.2500133514404,"hidden":false,"anchorPoint":{"pointX":0.5,"pointY":0.5}},"layers":[{"animations":[],"layers":[],"initialState":{"affineTransform":[1,0,0,1,0,0],"masksToBounds":false,"rotation":0,"scale":1,"position":{"pointX":393.39697265625,"pointY":238.6250066757202},"width":135,"sublayerTransform":[1,0,0,0,0,1,0,0,0,0,1,0,0,0,0,1],"contentsRect":{"y":0,"x":0,"width":1,"height":1},"opacity":1,"edgeAntialiasingMask":0,"height":49,"hidden":false,"anchorPoint":{"pointX":2.418518518518519,"pointY":-1.673469387755102}},"texture":"FF3CC4C1690EBFC336B569AD818503F8"}]},{"animations":[],"initialState":{"affineTransform":[1,0,0,1,0,0],"masksToBounds":false,"rotation":0,"scale":1,"position":{"pointX":960.0000057220459,"pointY":540},"width":801.7939567565918,"sublayerTransform":[1,0,0,0,0,1,0,0,0,0,1,0,0,0,0,1],"contentsRect":{"y":0,"x":0,"width":1,"height":1},"opacity":1,"edgeAntialiasingMask":15,"height":467.2500133514404,"hidden":false,"anchorPoint":{"pointX":0.5,"pointY":0.5}},"layers":[{"animations":[],"layers":[],"initialState":{"affineTransform":[1,0,0,1,0,0],"masksToBounds":false,"rotation":0,"scale":1,"position":{"pointX":393.39697265625,"pointY":238.6250066757202},"width":329,"sublayerTransform":[1,0,0,0,0,1,0,0,0,0,1,0,0,0,0,1],"contentsRect":{"y":0,"x":0,"width":1,"height":1},"opacity":1,"edgeAntialiasingMask":0,"height":56,"hidden":false,"anchorPoint":{"pointX":1.168693009118541,"pointY":3.892857142857143}},"texture":"2669DFB488A018FBD24B4099CC30365F"}]},{"animations":[],"initialState":{"affineTransform":[1,0,0,1,0,0],"masksToBounds":false,"rotation":0,"scale":1,"position":{"pointX":960.0000057220459,"pointY":540},"width":801.7939567565918,"sublayerTransform":[1,0,0,0,0,1,0,0,0,0,1,0,0,0,0,1],"contentsRect":{"y":0,"x":0,"width":1,"height":1},"opacity":1,"edgeAntialiasingMask":15,"height":467.2500133514404,"hidden":false,"anchorPoint":{"pointX":0.5,"pointY":0.5}},"layers":[{"animations":[],"layers":[],"initialState":{"affineTransform":[1,0,0,1,0,0],"masksToBounds":false,"rotation":0,"scale":1,"position":{"pointX":393.3969726562501,"pointY":238.6250066757202},"width":349,"sublayerTransform":[1,0,0,0,0,1,0,0,0,0,1,0,0,0,0,1],"contentsRect":{"y":0,"x":0,"width":1,"height":1},"opacity":1,"edgeAntialiasingMask":0,"height":59,"hidden":false,"anchorPoint":{"pointX":1.101719197707737,"pointY":-2.694915254237288}},"texture":"29860A4B0A24BD2A15089EA811089764"}]},{"animations":[],"initialState":{"affineTransform":[1,0,0,1,0,0],"masksToBounds":false,"rotation":0,"scale":1,"position":{"pointX":960.0000057220459,"pointY":540},"width":801.7939567565918,"sublayerTransform":[1,0,0,0,0,1,0,0,0,0,1,0,0,0,0,1],"contentsRect":{"y":0,"x":0,"width":1,"height":1},"opacity":1,"edgeAntialiasingMask":15,"height":467.2500133514404,"hidden":false,"anchorPoint":{"pointX":0.5,"pointY":0.5}},"layers":[{"animations":[],"layers":[],"initialState":{"affineTransform":[1,0,0,1,0,0],"masksToBounds":false,"rotation":0,"scale":1,"position":{"pointX":393.39697265625,"pointY":238.6250066757202},"width":362,"sublayerTransform":[1,0,0,0,0,1,0,0,0,0,1,0,0,0,0,1],"contentsRect":{"y":0,"x":0,"width":1,"height":1},"opacity":1,"edgeAntialiasingMask":0,"height":49,"hidden":false,"anchorPoint":{"pointX":0.7417127071823204,"pointY":-0.1224489795918368}},"texture":"0AC018AA8FBCE68F03BCD66829515547"}]},{"animations":[],"initialState":{"affineTransform":[1,0,0,1,0,0],"masksToBounds":false,"rotation":0,"scale":1,"position":{"pointX":960.0000057220459,"pointY":540},"width":801.7939567565918,"sublayerTransform":[1,0,0,0,0,1,0,0,0,0,1,0,0,0,0,1],"contentsRect":{"y":0,"x":0,"width":1,"height":1},"opacity":1,"edgeAntialiasingMask":15,"height":467.2500133514404,"hidden":false,"anchorPoint":{"pointX":0.5,"pointY":0.5}},"layers":[{"animations":[],"layers":[],"initialState":{"affineTransform":[1,0,0,1,0,0],"masksToBounds":false,"rotation":0,"scale":1,"position":{"pointX":393.39697265625,"pointY":238.6250066757202},"width":362,"sublayerTransform":[1,0,0,0,0,1,0,0,0,0,1,0,0,0,0,1],"contentsRect":{"y":0,"x":0,"width":1,"height":1},"opacity":1,"edgeAntialiasingMask":0,"height":49,"hidden":false,"anchorPoint":{"pointX":0.7417127071823204,"pointY":1.428571428571429}},"texture":"0BB9A8DC3940BD163F1907342A5D26F8"}]},{"animations":[],"initialState":{"affineTransform":[1,0,0,1,0,0],"masksToBounds":false,"rotation":0,"scale":1,"position":{"pointX":960.0000057220459,"pointY":540},"width":801.7939567565918,"sublayerTransform":[1,0,0,0,0,1,0,0,0,0,1,0,0,0,0,1],"contentsRect":{"y":0,"x":0,"width":1,"height":1},"opacity":1,"edgeAntialiasingMask":15,"height":467.2500133514404,"hidden":false,"anchorPoint":{"pointX":0.5,"pointY":0.5}},"layers":[{"animations":[],"layers":[],"initialState":{"affineTransform":[1,0,0,1,0,0],"masksToBounds":false,"rotation":0,"scale":1,"position":{"pointX":393.39697265625,"pointY":238.6250066757202},"width":712,"sublayerTransform":[1,0,0,0,0,1,0,0,0,0,1,0,0,0,0,1],"contentsRect":{"y":0,"x":0,"width":1,"height":1},"opacity":1,"edgeAntialiasingMask":0,"height":59,"hidden":false,"anchorPoint":{"pointX":0.4585674157303371,"pointY":2.474576271186441}},"texture":"5561CD8E7383DBF5567B967881EA5AE7"}]},{"animations":[],"initialState":{"affineTransform":[1,0,0,1,0,0],"masksToBounds":false,"rotation":0,"scale":1,"position":{"pointX":381.643211364746,"pointY":540},"width":939.7834472656251,"sublayerTransform":[1,0,0,0,0,1,0,0,0,0,1,0,0,0,0,1],"contentsRect":{"y":0,"x":0,"width":1,"height":1},"opacity":1,"edgeAntialiasingMask":15,"height":939.7834472656251,"hidden":false,"anchorPoint":{"pointX":0.5,"pointY":0.5}},"layers":[{"animations":[],"layers":[],"initialState":{"affineTransform":[1,0,0,1,0,0],"masksToBounds":false,"rotation":0,"scale":1,"position":{"pointX":469.3918755006439,"pointY":469.3917236328127},"width":944,"sublayerTransform":[1,0,0,0,0,1,0,0,0,0,1,0,0,0,0,1],"contentsRect":{"y":0,"x":0,"width":1,"height":1},"opacity":1,"edgeAntialiasingMask":0,"height":943,"hidden":true,"anchorPoint":{"pointX":0.5001518678311201,"pointY":0.5000000000000001}},"texture":"ABFB53E36D1904BADCB2552C2F842730"}]},{"animations":[],"initialState":{"affineTransform":[1,0,0,1,0,0],"masksToBounds":false,"rotation":0,"scale":1,"position":{"pointX":1348.625366210938,"pointY":540},"width":705.6670188903809,"sublayerTransform":[1,0,0,0,0,1,0,0,0,0,1,0,0,0,0,1],"contentsRect":{"y":0,"x":0,"width":1,"height":1},"opacity":1,"edgeAntialiasingMask":15,"height":315.2499914169312,"hidden":false,"anchorPoint":{"pointX":0.5,"pointY":0.5}},"layers":[{"animations":[],"layers":[],"initialState":{"affineTransform":[1,0,0,1,0,0],"masksToBounds":false,"rotation":0,"scale":1,"position":{"pointX":371.7081432342529,"pointY":164.1249957084656},"width":628,"sublayerTransform":[1,0,0,0,0,1,0,0,0,0,1,0,0,0,0,1],"contentsRect":{"y":0,"x":0,"width":1,"height":1},"opacity":1,"edgeAntialiasingMask":0,"height":89,"hidden":true,"anchorPoint":{"pointX":0.5246815286624203,"pointY":1.48876404494382}},"texture":"A5BBE620C3D5C2D755DCB8E756B0AAED"}]},{"animations":[],"initialState":{"affineTransform":[1,0,0,1,0,0],"masksToBounds":false,"rotation":0,"scale":1,"position":{"pointX":1348.625366210938,"pointY":540},"width":705.6670188903809,"sublayerTransform":[1,0,0,0,0,1,0,0,0,0,1,0,0,0,0,1],"contentsRect":{"y":0,"x":0,"width":1,"height":1},"opacity":1,"edgeAntialiasingMask":15,"height":315.2499914169312,"hidden":false,"anchorPoint":{"pointX":0.5,"pointY":0.5}},"layers":[{"animations":[],"layers":[],"initialState":{"affineTransform":[1,0,0,1,0,0],"masksToBounds":false,"rotation":0,"scale":1,"position":{"pointX":371.7081432342529,"pointY":164.1249957084656},"width":572,"sublayerTransform":[1,0,0,0,0,1,0,0,0,0,1,0,0,0,0,1],"contentsRect":{"y":0,"x":0,"width":1,"height":1},"opacity":1,"edgeAntialiasingMask":0,"height":113,"hidden":true,"anchorPoint":{"pointX":0.5288461538461539,"pointY":-0.172566371681416}},"texture":"03A700F694C19CBF914C99E266C25F0D"}]}]}}]}